hylpg/__cli__.py
hylpg/__init__.py
hylpg/_version.py
hylpg/conf/__init__.py
hylpg/conf/about/hylpg.yaml
hylpg/py.typed
hyfi_lpg-0.1.0.dist-info/LICENSE
hyfi_lpg-0.1.0.dist-info/METADATA
hyfi_lpg-0.1.0.dist-info/WHEEL
hyfi_lpg-0.1.0.dist-info/entry_points.txt
hyfi_lpg-0.1.0.dist-info/RECORD
