Metadata-Version: 2.1
Name: hyfi-lpg
Version: 0.1.0
Summary: HyFI-LPG is an LLM powered gleaning tool for HyFI.
Home-page: https://hyfi-lpg.entelecheia.ai
License: MIT
Author: Young Joon Lee
Author-email: entelecheia@hotmail.com
Requires-Python: >=3.9,<3.13
Classifier: License :: OSI Approved :: MIT License
Classifier: Programming Language :: Python :: 3
Classifier: Programming Language :: Python :: 3.9
Classifier: Programming Language :: Python :: 3.10
Classifier: Programming Language :: Python :: 3.11
Classifier: Programming Language :: Python :: 3.12
Requires-Dist: click (>=8.1.3,<9.0.0)
Requires-Dist: hyfi (>=1.36.4,<2.0.0)
Project-URL: Repository, https://github.com/entelecheia/hyfi-lpg
